odoo/addons/contact_search_form/README.rst
odoo/addons/contact_search_form/__init__.py
odoo/addons/contact_search_form/__manifest__.py
odoo/addons/contact_search_form/i18n/contact_search_form.pot
odoo/addons/contact_search_form/i18n/de.po
odoo/addons/contact_search_form/i18n/en_US.po
odoo/addons/contact_search_form/i18n/fr.po
odoo/addons/contact_search_form/i18n/it.po
odoo/addons/contact_search_form/models/__init__.py
odoo/addons/contact_search_form/models/contact_search.py
odoo/addons/contact_search_form/readme/CONFIGURE.rst
odoo/addons/contact_search_form/readme/DESCRIPTION.rst
odoo/addons/contact_search_form/readme/USAGE.rst
odoo/addons/contact_search_form/security/gdpr_security.xml
odoo/addons/contact_search_form/security/ir.model.access.csv
odoo/addons/contact_search_form/static/description/icon.png
odoo/addons/contact_search_form/static/description/index.html
odoo/addons/contact_search_form/views/contact_search.xml
odoo11_addon_contact_search_form-11.0.1.0.0.99.dev8.dist-info/METADATA
odoo11_addon_contact_search_form-11.0.1.0.0.99.dev8.dist-info/WHEEL
odoo11_addon_contact_search_form-11.0.1.0.0.99.dev8.dist-info/top_level.txt
odoo11_addon_contact_search_form-11.0.1.0.0.99.dev8.dist-info/RECORD
